README.rst
setup.py
etree_trunc/__init__.py
etree_trunc.egg-info/PKG-INFO
etree_trunc.egg-info/SOURCES.txt
etree_trunc.egg-info/dependency_links.txt
etree_trunc.egg-info/top_level.txt